actionsBy/__init__.py
actionsBy/actions.py
actionsBy-1.0.1.dist-info/LICENSE
actionsBy-1.0.1.dist-info/METADATA
actionsBy-1.0.1.dist-info/WHEEL
actionsBy-1.0.1.dist-info/top_level.txt
actionsBy-1.0.1.dist-info/RECORD
