Metadata-Version: 2.1
Name: actionsBy
Version: 1.0.1
Summary: This package contains the base file where we can perform the click, displayed, sendkeys using any locators like id, name, xpath by just pass the parameters to the function
Author: Jagadeesh
Author-email: jagadeeshsaratha@gmail.com
License-File: LICENSE
